implements.py
implements-0.3.0.dist-info/LICENSE
implements-0.3.0.dist-info/METADATA
implements-0.3.0.dist-info/WHEEL
implements-0.3.0.dist-info/top_level.txt
implements-0.3.0.dist-info/RECORD
