Metadata-Version: 2.1
Name: implements
Version: 0.3.0
Summary: Pythonic interfaces using decorators
Home-page: http://implements.readthedocs.io
Author: Kamil Sindi <ksindi@ksindi.com>
Maintainer: Kamil Sindi
Maintainer-email: ksindi@ksindi.com
License: Apache License, Version 2.0
Keywords: implements,interfaces
Platform: UNKNOWN
Classifier: Development Status :: 5 - Production/Stable
Classifier: Intended Audience :: Developers
Classifier: License :: OSI Approved :: Apache Software License
Classifier: Natural Language :: English
Classifier: Programming Language :: Python :: 3
Classifier: Programming Language :: Python :: 3.6
Classifier: Programming Language :: Python :: 3.7
Classifier: Programming Language :: Python :: 3.8
Requires-Dist: setuptools-scm (>=1.15.0)
